code/cpu/neuron/neuron.v
`timescale 1ns/100ps

module neuron(CLK, RESET, SPIKED, I, a, b, c, d);
    // Izhikevich neuron model using fixed-point arithmetic
    // All values are represented as signed 32-bit fixed point with 16 fractional bits
    // Format: Q16.16 (16 integer bits, 16 fractional bits)
    
    localparam signed [31:0] FIXED_0_04 = 32'h00000A3D;  // 0.04 in Q16.16
    localparam signed [31:0] FIXED_5    = 32'h00050000;  // 5.0 in Q16.16
    localparam signed [31:0] FIXED_140  = 32'h008C0000;  // 140.0 in Q16.16
    localparam signed [31:0] FIXED_30   = 32'h001E0000;  // 30.0 in Q16.16

    input CLK, RESET;
    input signed [31:0] I, a, b, c, d;  // Fixed-point Q16.16 format
    output reg SPIKED;

    reg signed [31:0] V;   // Membrane potential
    reg signed [31:0] U;   // Recovery variable

    // Intermediate calculation wires
    wire signed [63:0] v_squared_full;
    wire signed [31:0] v_squared;
    wire signed [63:0] term1_full, term2_full, term3_full, term4_full;
    wire signed [31:0] term1, term2, term3;
    wire signed [31:0] v_prime;
    
    wire signed [63:0] u_term1_full, u_term2_full;
    wire signed [31:0] u_term1, u_term2;
    wire signed [31:0] u_prime;

    /******************************** V' Calculation ********************************/
    // V' = 0.04*V^2 + 5*V + 140 - U + I
    
    // V^2 (multiply and scale back)
    assign v_squared_full = V * V;
    assign v_squared = v_squared_full[47:16];  // Extract Q16.16 result
    
    // 0.04 * V^2
    assign term1_full = FIXED_0_04 * v_squared;
    assign term1 = term1_full[47:16];
    
    // 5 * V
    assign term2_full = FIXED_5 * V;
    assign term2 = term2_full[47:16];
    
    // Combine: 0.04*V^2 + 5*V + 140 - U + I
    assign term3 = term1 + term2 + FIXED_140 - U + I;
    assign v_prime = term3;

    /******************************** U' Calculation ********************************/
    // U' = a * (b*V - U)
    
    // b * V
    assign u_term1_full = b * V;
    assign u_term1 = u_term1_full[47:16];
    
    // a * (b*V - U)
    assign u_term2_full = a * (u_term1 - U);
    assign u_prime = u_term2_full[47:16];

    /******************************** Spike Detection ********************************/
    // Spike when V >= 30
    wire spike_condition;
    assign spike_condition = (V >= FIXED_30);

    /******************************** State Update ********************************/
    always @ (posedge CLK) begin
        if (RESET) begin
            V <= c;  // Initialize to resting potential
            U <= b;  // Initialize recovery variable
            SPIKED <= 1'b0;
        end
        else begin
            if (spike_condition) begin
                // Spike detected - reset
                V <= c;
                U <= U + d;
                SPIKED <= 1'b1;
            end
            else begin
                // Normal update
                V <= V + v_prime;  // Simple Euler integration
                U <= U + u_prime;
                SPIKED <= 1'b0;
            end
        end
    end
    
endmodule

code/cpu/neuron/neuron_tb.v
w`include "neuron/neuron.v"
`timescale 1ns/100ps

module neuron_tb;
    parameter CLOCK_PERIOD = 10;

    // Inputs
    reg CLK, RESET;
    reg [31:0] I, a, b, c, d;
    
    // Outputs
    wire SPIKED;

    // Instantiate the neuron
    neuron dut (
        .CLK(CLK),
        .RESET(RESET),
        .SPIKED(SPIKED),
        .I(I),
        .a(a),
        .b(b),
        .c(c),
        .d(d)
    );

    // Clock generation
    initial begin
        CLK = 1'b0;
        forever #(CLOCK_PERIOD/2) CLK = ~CLK;
    end

    // VCD dump for waveform viewing
    initial begin
        $dumpfile("neuron_tb.vcd");
        $dumpvars(0, dut);
    end

    // Test stimulus
    integer cycle;
    initial begin
        $display("========================================");
        $display("   Izhikevich Neuron Model Testbench");
        $display("========================================\n");

        // Initialize
        RESET = 1'b0;
        I = 32'h00000000;  // 0.0
        a = 32'h3d23d70a;  // 0.04
        b = 32'h3e4ccccd;  // 0.2
        c = 32'hc2480000;  // -50.0
        d = 32'h40000000;  // 2.0
        cycle = 0;

        // Wait for initial setup
        #5;

        $display("Test 1: Regular Spiking (RS) Neuron");
        $display("Parameters: a=0.02, b=0.2, c=-65, d=8");
        $display("Input current: I=10");
        $display("----------------------------------------");
        
        // Regular Spiking parameters
        a = 32'h3ca3d70a;  // 0.02
        b = 32'h3e4ccccd;  // 0.2
        c = 32'hc2820000;  // -65.0
        d = 32'h41000000;  // 8.0
        I = 32'h41200000;  // 10.0

        // Reset neuron
        RESET = 1'b1;
        #CLOCK_PERIOD;
        RESET = 1'b0;

        // Simulate for 100 cycles
        for (cycle = 0; cycle < 100; cycle = cycle + 1) begin
            #CLOCK_PERIOD;
            if (SPIKED) begin
                $display("Cycle %3d: SPIKE! V=%h, U=%h", cycle, dut.V, dut.U);
            end
        end

        $display("\nTest 2: Fast Spiking (FS) Neuron");
        $display("Parameters: a=0.1, b=0.2, c=-65, d=2");
        $display("Input current: I=10");
        $display("----------------------------------------");
        
        // Fast Spiking parameters
        a = 32'h3dcccccd;  // 0.1
        b = 32'h3e4ccccd;  // 0.2
        c = 32'hc2820000;  // -65.0
        d = 32'h40000000;  // 2.0
        I = 32'h41200000;  // 10.0

        // Reset neuron
        RESET = 1'b1;
        #CLOCK_PERIOD;
        RESET = 1'b0;

        // Simulate for 100 cycles
        for (cycle = 0; cycle < 100; cycle = cycle + 1) begin
            #CLOCK_PERIOD;
            if (SPIKED) begin
                $display("Cycle %3d: SPIKE! V=%h, U=%h", cycle, dut.V, dut.U);
            end
        end

        $display("\nTest 3: Chattering (CH) Neuron");
        $display("Parameters: a=0.02, b=0.2, c=-50, d=2");
        $display("Input current: I=10");
        $display("----------------------------------------");
        
        // Chattering parameters
        a = 32'h3ca3d70a;  // 0.02
        b = 32'h3e4ccccd;  // 0.2
        c = 32'hc2480000;  // -50.0
        d = 32'h40000000;  // 2.0
        I = 32'h41200000;  // 10.0

        // Reset neuron
        RESET = 1'b1;
        #CLOCK_PERIOD;
        RESET = 1'b0;

        // Simulate for 100 cycles
        for (cycle = 0; cycle < 100; cycle = cycle + 1) begin
            #CLOCK_PERIOD;
            if (SPIKED) begin
                $display("Cycle %3d: SPIKE! V=%h, U=%h", cycle, dut.V, dut.U);
            end
        end

        $display("\nTest 4: Low-Threshold Spiking (LTS) Neuron");
        $display("Parameters: a=0.02, b=0.25, c=-65, d=2");
        $display("Input current: I=5");
        $display("----------------------------------------");
        
        // LTS parameters
        a = 32'h3ca3d70a;  // 0.02
        b = 32'h3e800000;  // 0.25
        c = 32'hc2820000;  // -65.0
        d = 32'h40000000;  // 2.0
        I = 32'h40a00000;  // 5.0

        // Reset neuron
        RESET = 1'b1;
        #CLOCK_PERIOD;
        RESET = 1'b0;

        // Simulate for 100 cycles
        for (cycle = 0; cycle < 100; cycle = cycle + 1) begin
            #CLOCK_PERIOD;
            if (SPIKED) begin
                $display("Cycle %3d: SPIKE! V=%h, U=%h", cycle, dut.V, dut.U);
            end
        end

        $display("\nTest 5: Variable Input Current");
        $display("Parameters: a=0.02, b=0.2, c=-65, d=8");
        $display("Ramping input current from 0 to 15");
        $display("----------------------------------------");
        
        // Regular Spiking parameters
        a = 32'h3ca3d70a;  // 0.02
        b = 32'h3e4ccccd;  // 0.2
        c = 32'hc2820000;  // -65.0
        d = 32'h41000000;  // 8.0

        // Reset neuron
        RESET = 1'b1;
        #CLOCK_PERIOD;
        RESET = 1'b0;

        // Ramp input current
        for (cycle = 0; cycle < 150; cycle = cycle + 1) begin
            // Linearly increase input current every 10 cycles
            if (cycle % 10 == 0) begin
                I = I + 32'h3f800000;  // Add 1.0
                $display("Cycle %3d: I increased to ~%0d", cycle, (cycle/10));
            end
            #CLOCK_PERIOD;
            if (SPIKED) begin
                $display("Cycle %3d: SPIKE! V=%h, U=%h", cycle, dut.V, dut.U);
            end
        end

        $display("\n========================================");
        $display("   Testbench completed successfully");
        $display("========================================");
        
        #(CLOCK_PERIOD * 10);
        $finish;
    end

    // Monitor for debugging
    initial begin
        $monitor("Time=%0t CLK=%b RESET=%b I=%h SPIKED=%b V=%h U=%h", 
                 $time, CLK, RESET, I, SPIKED, dut.V, dut.U);
    end

endmodule

code/cpu/neuron_tb.vcd
$date
	Sat Dec 06 23:48:32 2025
$end
$version
	Icarus Verilog
$end
$timescale
	100ps
$end
$scope module neuron_tb $end
$scope module dut $end
$var wire 1 ! CLK $end
$var wire 32 " I [31:0] $end
$var wire 1 # RESET $end
$var wire 32 $ a [31:0] $end
$var wire 32 % b [31:0] $end
$var wire 32 & c [31:0] $end
$var wire 32 ' d [31:0] $end
$var wire 32 ( v_prime [31:0] $end
$var wire 64 ) v_squared_full [63:0] $end
$var wire 32 * v_squared [31:0] $end
$var wire 64 + u_term2_full [63:0] $end
$var wire 64 , u_term1_full [63:0] $end
$var wire 32 - u_term1 [31:0] $end
$var wire 32 . u_prime [31:0] $end
$var wire 32 / term3 [31:0] $end
$var wire 64 0 term2_full [63:0] $end
$var wire 32 1 term2 [31:0] $end
$var wire 64 2 term1_full [63:0] $end
$var wire 32 3 term1 [31:0] $end
$var wire 1 4 spike_condition $end
$var parameter 32 5 FIXED_0_04 $end
$var parameter 32 6 FIXED_140 $end
$var parameter 32 7 FIXED_30 $end
$var parameter 32 8 FIXED_5 $end
$var reg 1 9 SPIKED $end
$var reg 32 : U [31:0] $end
$var reg 32 ; V [31:0] $end
$upscope $end
$upscope $end
$enddefinitions $end
$comment Show the parameter values. $end
$dumpall
b1010000000000000000 8
b111100000000000000000 7
b100011000000000000000000 6
b101000111101 5
$end
#0
$dumpvars
bx ;
bx :
x9
x4
bx 3
bx 2
bx 1
bx 0
bx /
bx .
bx -
bx ,
bx +
bx *
bx )
bx (
b1000000000000000000000000000000 '
b11000010010010000000000000000000 &
b111110010011001100110011001101 %
b111101001000111101011100001010 $
0#
b0 "
0!
$end
#50
b11010010110111101111111000100111 (
b11010010110111101111111000100111 /
b10111101011100101011110100 3
b100001111100110110100010110010 .
b101111010111001010111101000000000000000000 2
b1001010000001000000000000000000 *
b11001100100010100000000000000000 1
b1111001101111000001000011111001101101000101100100011000000000010 +
b1001011001100101101000011010 -
09
b111110010011001100110011001101 :
b111011000101010010100000010000000000000000000000000000000000 )
b1111111111111110110011001000101000000000000000000000000000000000 0
b1111000100001001000010010110011001011010000110100000000000000000 ,
04
b11000010100000100000000000000000 ;
1#
b1000001001000000000000000000000 "
b1000001000000000000000000000000 '
b11000010100000100000000000000000 &
b111100101000111101011100001010 $
1!
#100
0!
#150
b101001101100111111011010 3
b11010101101010101100011101101 .
b1010011011001111110110101000111110001101 2
b10000010010101111111110010001 *
b11101010111001001111011011000011 1
b10000001000011001100111011000110 -
b11001100111101111001000100011110 (
b11001100111101111001000100011110 /
b1100101100100001000110101011010101011000111011011001110111000110 +
b1100000010000000011010101111111 :
b10110001101000000100000100101011111111100100010110100111110001 )
b1111111111111101111010101110010011110110110000110000000000000000 0
b1110011000001101100000010000110011001110110001101001100100111011 ,
b10010101011000001111111000100111 ;
1!
0#
#200
0!
#250
b11111111001101101001010001010010 3
b11010110010110000110100101000101 .
b1111111111111111111111110011011010010100010100100010100010100110 2
b11101100010100111010001110011110 *
b11101011101110101100110001011001 1
b11110011101010101001000110010001 -
b10110001101001111101001000111111 (
b10110001101001111101001000111111 /
b1101111111110011110101100101100001101001010001010011001001110010 +
b1111010111101011000111001101100 :
b10010111000111111011000101001110100011100111100010100010011001 )
b1111010111011101011001100010110010000000000000000 0
b1011111101110111100111010101010010001100100011011011001000001 ,
14
b1100010010110001000111101000101 ;
1!
#300
0!
#350
b10111101011100101011110100 3
b11111111100110110011100101000001 .
b101111010111001010111101000000000000000000 2
b1001010000001000000000000000000 *
b11001100100010100000000000000000 1
b1001011001100101101000011010 -
19
b1010101001101100011110010001000 (
b1010101001101100011110010001000 /
b1001001010111111111111001101100111001010000010001011011001100 +
b10111011111101011000111001101100 :
b111011000101010010100000010000000000000000000000000000000000 )
b1111111111111110110011001000101000000000000000000000000000000000 0
b1111000100001001000010010110011001011010000110100000000000000000 ,
04
b11000010100000100000000000000000 ;
1!
#400
0!
#450
b11111100001000111010101010001100 3
b1101001100001011111001010001001 .
b1111111111111111111111000010001110101010100011000000111010010000 2
b10011111011101111000000111010000 *
b1110110100110010010111010101000 1
b10111100010101001011011100100100 -
09
b11111000110110000001000110000111 (
b11111000110110000001000110000111 /
b101110011010011000010111110010100010010100101110100110 +
b10111011100100001100011110101101 :
b1000110010100111110111011110000001110100000000100001000000 )
b11101101001100100101110101010000000000000000000 0
b10111000101101111000101010010110111001001001101100011101000 ,
14
b10111101110000011110010001000 ;
1!
#500
0!
#550
b10111101011100101011110100 3
b1000101000101011010010110111000 .
b101111010111001010111101000000000000000000 2
b1001010000001000000000000000000 *
b11001100100010100000000000000000 1
b1001011001100101101000011010 -
19
b10100100110110000001101000111 (
b10100100110110000001101000111 /
b1100001010010001010001010110100101101110000100001101000010 +
b11111100100100001100011110101101 :
b111011000101010010100000010000000000000000000000000000000000 )
b1111111111111110110011001000101000000000000000000000000000000000 0
b1111000100001001000010010110011001011010000110100000000000000000 ,
04
b11000010100000100000000000000000 ;
1!
#600
0!
#650
b11111101001000010100100010001010 3
b10010111001110110100110000010001 .
b1111111111111111111111010010000101001000100010100100011110100000 2
b10111000001111010000000000100000 *
b110011100100010001000001100011 1
b11000010101100101000101111101100 -
09
b110000101101111110101110001000 (
b110000101101111110101110001000 /
b1110000111101101100101110011101101001100000100011001001001000110 +
b1000001101001100110110101100101 :
b11010000111101110000011110100000000001000001011110110110001 )
b1111111111111111001100111001000100010000011000110000000000000000 0
b1111011000001100110000101011001010001011111011000011001111011011 ,
b11010111000111010000001101000111 ;
1!
#700
0!
#750
b11011100100011110110010110 3
b11011111101111110101011011000110 .
b110111001000111101100101101110001001101001 2
b1010110001010111011011110011101 *
b100111001010001010101000001011 1
b11101011010100001111101101000100 -
b10010011011001010010111000101011 (
b10010011011001010010111000101011 /
b10001011101110111111011111101010110110001101001010000001100 +
b11011000111000011011100101110110 :
b111101010101100010101110110111100111011000101101100001 )
b1001110010100010101010000010110000000000000000 0
b111100111111010110101000011111011010001000010111111000011 ,
14
b111110101001110111011001111 ;
1!
#800
0!
#850
b10111101011100101011110100 3
b10001001010000000111011010000100 .
b101111010111001010111101000000000000000000 2
b1001010000001000000000000000000 *
b11001100100010100000000000000000 1
b1001011001100101101000011010 -
19
b11110111010010100001000101111110 (
b11110111010010100001000101111110 /
b1111110000011000100010010100000001110110100001000000001001101000 +
b11001111000011011100101110110 :
b111011000101010010100000010000000000000000000000000000000000 )
b1111111111111110110011001000101000000000000000000000000000000000 0
b1111000100001001000010010110011001011010000110100000000000000000 ,
04
b11000010100000100000000000000000 ;
1!
#900
0!
#950
b100100001001001101100000011 3
b11111010111101011100010011000 .
b1001000010010011011000000111001000000111101 2
b1110000111101111111111000000001 *
b10100000111111000101011101110110 1
b1011100101010000001101111000010 -
09
b1000100000010101100001001111111 (
b1000100000010101100001001111111 /
b10101111110010000111110101111010111000100110000010110111010000 +
b10100011001000100010111111111010 :
b1001101000000011100001111011111111110000000011111101000000100 )
b1111111111111110101000001111110001010111011101100000000000000000 0
b1110111011101010010111001010100000011011110000100110100111100110 ,
b10111001110011000001000101111110 ;
1!
#1000
0!
#1050
b11111100100111001110100110011010 3
b11010101011011100100000100010001 .
b1111111111111111111111001001110011101001100110101110001000101011 2
b10101011010011110010110010000111 *
b11110101001100100010001111110001 1
b1100001011000111010101100010001 -
b1110000111110100010010011111001 (
b1110000111110100010010011111001 /
b10010110100010110101010110111001000001000100010100000111110110 +
b11000010100000001110100010010010 :
b100101010110100111100101100100001110000100000001001 )
b1111111111111111111101010011001000100011111100010000000000000000 0
b1111111101111001011000010110001110101011000100010101110110011001 ,
b11111101110101101101001111111101 ;
1!
#1100
0!
#1150
b10100101001011100111000010 3
b11001011001011100000111010011 .
b101001010010111001110000100101101110101001 2
b1000000100010001110100111011101 *
b101010000101001101110011001110 1
b11011010111111001100000011000011 -
b11010110011001100110110011101101 (
b11010110011001100110110011101101 /
b111111100010000110010110010111000001110100111100011101000000 +
b10010111111011110010100110100011 :
b10111111111000010000001000100011101001110111011000110001100100 )
b10001010100001010011011100110011100000000000000000 0
b1101011110111110110101111110011000000110000110110010011111110 ,
14
b1101110110100001111100011110110 ;
1!
#1200
0!
#1250
b10111101011100101011110100 3
b11110011111101011011111000100000 .
b101111010111001010111101000000000000000000 2
b1001010000001000000000000000000 *
b11001100100010100000000000000000 1
b1001011001100101101000011010 -
19
b111000001111001010000101010001 (
b111000001111001010000101010001 /
b101101111010111100111111010110111110001000001101010110100110 +
b11011000111011110010100110100011 :
b111011000101010010100000010000000000000000000000000000000000 )
b1111111111111110110011001000101000000000000000000000000000000000 0
b1111000100001001000010010110011001011010000110100000000000000000 ,
04
b11000010100000100000000000000000 ;
1!
#1300
0!
#1350
b11111100000110001010011001100010 3
b10011111001001111000000010101010 .
b1111111111111111111111000001100010100110011000100010001011011010 2
b10011110011001000000110111100010 *
b11100101101110010010011010010101 1
b10010111011101010011010100111111 -
09
b1010110100110001110010100110100 (
b1010110100110001110010100110100 /
b1111001101010111100111110010011110000000101010100010101011011000 +
b11001100111001001110011111000011 :
b11011100111100110010000001101111000101111101110100001 )
b1111111111111111111001011011100100100110100101010000000000000000 0
b1111111010111000100101110111010100110101001111111011100111011101 ,
b11111010101111101010000101010001 ;
1!
#1400
0!
#1450
b11111010111011000100000011000111 3
b10100011100000010010000000011001 .
b1111111111111111111110101110110001000000110001111111101000000001 2
b10000001000011001101111100010101 *
b10010110101101011010000010011001 1
b10011001101000110000011111000100 -
b1100111010000010111100011110011 (
b1100111010000010111100011110011 /
b1100111000101000101000111000000100100000000110010100101001100110 +
b1101100000011000110100001101101 :
b1100111011000100000010000110011011111000101011000000100011001 )
b1100101101011010110100000100110010000000000000000 0
b1001111001011100110011010001100000111110001001011010010000001 ,
14
b1010001010101111000011010000101 ;
1!
#1500
0!
#1550
b10111101011100101011110100 3
b101111011111001001001010100010 .
b101111010111001010111101000000000000000000 2
b1001010000001000000000000000000 *
b11001100100010100000000000000000 1
b1001011001100101101000011010 -
19
b1100100000111110110001010000111 (
b1100100000111110110001010000111 /
b1010111100000001011110111110010010010101000101011101111000010 +
b10101101000011000110100001101101 :
b111011000101010010100000010000000000000000000000000000000000 )
b1111111111111110110011001000101000000000000000000000000000000000 0
b1111000100001001000010010110011001011010000110100000000000000000 ,
04
b11000010100000100000000000000000 ;
1!
#1600
0!
#1650
b11001010001011010111011111 3
b11101101001110001011011001011101 .
b110010100010110101110111111011000100010101 2
b1001110111111010010011110111001 *
b11000001001001101110110010100011 1
b10101100101011010111101111010011 -
09
b101001011100101010011101110011 (
b101001011100101010011101110011 /
b1111010010101001111011010011100010110110010111011010001110101000 +
b11011100100010001111101100001111 :
b10111010100010011101111110100100111101110011010001100110001 )
b110000010010011011101100101000110000000000000000 0
b100101100110101011001010110101111011110100110111101000011011 ,
14
b100110101000010110001010000111 ;
1!
#1700
0!
#1750
b10111101011100101011110100 3
b11111111010100000011100101111000 .
b101111010111001010111101000000000000000000 2
b1001010000001000000000000000000 *
b11001100100010100000000000000000 1
b1001011001100101101000011010 -
19
b11110011101000101100111111100101 (
b11110011101000101100111111100101 /
b1111101100111010111111110101000000111001011110001111001101101110 +
b11101100010001111101100001111 :
b111011000101010010100000010000000000000000000000000000000000 )
b1111111111111110110011001000101000000000000000000000000000000000 0
b1111000100001001000010010110011001011010000110100000000000000000 ,
04
b11000010100000100000000000000000 ;
1!
#1800
0!
#1850
b11111101010100110001101011000011 3
b10100100111110000111110010100011 .
b1111111111111111111111010101001100011010110000110110111101001100 2
b10111101000110101011110100111100 *
b10001110101110000000111101111001 1
b11000010001100010101111100100000 -
09
b10110000110111011111010110110101 (
b10110000110111011111010110110101 /
b1110101010000110101001001111100001111100101000110010100011111010 +
b11100110110010011010010000111 :
b1010101001110101111010001101010111101001111000010001011011001 )
b1111111111111110100011101011100000001111011110010000000000000000 0
b1110111000000110110000100011000101011111001000001111011001100001 ,
b10110110001001001100111111100101 ;
1!
#1900
0!
#1950
b10010111000111000101010111 3
b1000001100110101001001110001001 .
b100101110001110001010101110011011010110110 2
b111011000010011001101011101110 *
b11000011011101110000000010 1
b10010011000101101010100001100110 -
b10000101010001001001110000101111 (
b10000101010001001001110000101111 /
b1111010011101110010000011001101010010011100010010000110001011000 +
b11000001110100011011000100101010 :
b10100101110011001110110000100110011010111011100110000010100100 )
b10000000110000110111011100000000100000000000000000 0
b1100100010001100100110001011010101000011001101111010001010010 ,
14
b1100111000000101100010110011010 ;
1!
#2000
0!
#2050
b10111101011100101011110100 3
b1101110001101110110010000000 .
b101111010111001010111101000000000000000000 2
b1001010000001000000000000000000 *
b11001100100010100000000000000000 1
b1001011001100101101000011010 -
19
b1110010110100001100111001010 (
b1110010110100001100111001010 /
b110001111000011011100011011101100100000000010100101100000 +
b10110100011011000100101010 :
b111011000101010010100000010000000000000000000000000000000000 )
b1111111111111110110011001000101000000000000000000000000000000000 0
b1111000100001001000010010110011001011010000110100000000000000000 ,
04
b11000010100000100000000000000000 ;
1!
#2100
0!
#2150
b10000011111110111101001101 3
b11110110001011100011011001000000 .
b100000111111101111010011011000101011100101 2
b110011100100001001010111001001 *
b10100010011001000000011110010 1
b101001111000000011100011000101 -
09
b1000111011011111101001010010101 (
b1000111011011111101001010010101 /
b10111111100111101100010111000110110010000001011110000001110 +
b10000100110001001110110101010 :
b100010101110001100111001000010010101110010010001001101100100 )
b1111111111111111000101000100110010000000111100100000000000000000 0
b1111010010000111001010011110000000111000110001011001111011000010 ,
b11010000110111000001100111001010 ;
1!
#2200
0!
#2250
b11010100000001101010101011 3
b1111010001011011001001000100010 .
b110101000000011010101010110001011010000101 2
b1010010110101100010100111101001 *
b1111001011110111001110111011011 1
b10101101001110010010001101011011 -
b10110111101100001110010010011100 (
b10110111101100001110010010011100 /
b1110101011001001011110100010110110010010001000100000000101101010 +
b110110001101101001111101010 :
b1001001110010100101101011000101001111010010100101101000001 )
b11110010111101110011101110110110000000000000000 0
b10111101001101011010011100100100011010110111111110000010011 ,
14
b11000010010111110110001011111 ;
1!
#2300
0!
#2350
b10111101011100101011110100 3
b1110111101000000011101001111101 .
b101111010111001010111101000000000000000000 2
b1001010000001000000000000000000 *
b11001100100010100000000000000000 1
b1001011001100101101000011010 -
19
b11001001011001001111011100001010 (
b11001001011001001111011100001010 /
b1111000100111001011101111010000000111010011111011000110111100000 +
b1000111110001101101001111101010 :
b111011000101010010100000010000000000000000000000000000000000 )
b1111111111111110110011001000101000000000000000000000000000000000 0
b1111000100001001000010010110011001011010000110100000000000000000 ,
04
b11000010100000100000000000000000 ;
1!
#2400
0!
#2450
b11111100111001110011110110011010 3
b11101111100010100101010101101001 .
b1111111111111111111111001110011100111101100110101001110111101100 2
b10110010100100011011000001011100 *
b10111011100000101101001100110010 1
b11011100001001101011111000111 -
09
b111010101011110000001001100101 (
b111010101011110000001001100101 /
b1010111010001111011111000101001010101011010010111110111000000 +
b10111111011001110000111001100111 :
b11010010100110101100101001000110110000010111000100110001100100 )
b1111111111111101101110111000001011010011001100100000000000000000 0
b1110001110111111000110111000010011010111110001111100101100000010 ,
b10001011111001101111011100001010 ;
1!
#2500
0!
#2550
b11111100111110100100010100 3
b1101001011000001100011100000110 .
b111111001111101001000101001111111100000011 2
b1100010110101100000001000111111 *
b11100000111011011101111100101011 1
b11001000000000111011111010001 -
b1110111100111000110010001101111 (
b1110111100111000110010001101111 /
b1100100011111011010010110000011000111000001101001111100001010 +
b10101110111100010110001111010000 :
b110011100000011000101101011000000010001111110001111000100001 )
b1111111111111110111000001110110111011111001010110000000000000000 0
b1111001000000111000110010000000001110111110100010011000111100011 ,
b11000110100101011111100101101111 ;
1!
#2600
0!
#2650
b100011101000100110101000111 3
b1100110010010001000100011011001 .
b1000111010001001101010001111010011101010111 2
b1101111011000000101010100100011 *
b110110111110111101010101010110 1
b11011011011100011001001100001010 -
b1100100110010011111011111000111 (
b1100100110010011111011111000111 /
b1111000110010100011001100100100010001000110110011011111000001000 +
b11000010100100010101011010110 :
b111100011100011011110110000001010101001000110000110010000100 )
b1001101101111101111010101010101100000000000000000 0
b111100100010110110110111000110010011000010100001001011000110 ,
14
b111110001100100101110111011110 ;
1!
#2700
0!
#2750
b10111101011100101011110100 3
b10010100110010111101110011000111 .
b101111010111001010111101000000000000000000 2
b1001010000001000000000000000000 *
b11001100100010100000000000000000 1
b1001011001100101101000011010 -
19
b10110111110110011010000000011110 (
b10110111110110011010000000011110 /
b1110110100010001100101001100101111011100110001111111010010101000 +
b1011001010100100010101011010110 :
b111011000101010010100000010000000000000000000000000000000000 )
b1111111111111110110011001000101000000000000000000000000000000000 0
b1111000100001001000010010110011001011010000110100000000000000000 ,
04
b11000010100000100000000000000000 ;
1!
#2800
0!
#2850
b100101100100000011111101011 3
b10101010001010110010100101010111 .
b1001011001000000111111010111010001111010101 2
b1110101011001111101000101111001 *
b1100011110010100010000010010110 1
b11100101110111011100101111011111 -
09
b10111100000010100010000011100100 (
b10111100000010100010000011100100 /
b1111111000001011101010100010101100101001010101110001100010010100 +
b11101110000111100000011110011101 :
b11101001111011011101010110011111010001011110011000001110000100 )
b10011000111100101000100000100101100000000000000000 0
b1110111000110111001011101110111001011110111110010000000000110 ,
14
b1111010010110111010000000011110 ;
1!
#2900
0!
#2950
b10111101011100101011110100 3
b11001111101100110001010110110001 .
b101111010111001010111101000000000000000000 2
b1001010000001000000000000000000 *
b11001100100010100000000000000000 1
b1001011001100101101000011010 -
19
b11100010000011011100001101010111 (
b11100010000011011100001101010111 /
b1111011100010000110011111011001100010101101100010011001111100010 +
b101111000111100000011110011101 :
b111011000101010010100000010000000000000000000000000000000000 )
b1111111111111110110011001000101000000000000000000000000000000000 0
b1111000100001001000010010110011001011010000110100000000000000000 ,
04
b11000010100000100000000000000000 ;
1!
#3000
0!
#3050
b11111111110110100111010100100100 3
b1000000100100000100110101101111 .
b1111111111111111111111111101101001110101001001001010110100000011 2
b11111100010101010100100000111111 *
b110110110011101101000010110011 1
b1100010110101100110011010011100 -
09
b1111001100001000010100010001001 (
b1111001100001000010100010001001 /
b1011110110001010000001001000001001101011011110101111100001100 +
b11111110110100010001110101001110 :
b10000010101000111111000101010101001000001111111010011110010001 )
b1111111111111110001101101100111011010000101100110000000000000000 0
b1110100110111111011000101101011001100110100111001100000010101011 ,
b10100100100011111100001101010111 ;
1!
#3100
0!
#3150
b11111100101011001000010001110100 3
b11011011111010000100011001110111 .
b1111111111111111111111001010110010000100011101001110000110000001 2
b10101100110101010101110010010101 *
b10010110011000111001101101100000 1
b11011001000110100011110001101010 -
b10010101010110101011010100010111 (
b10010101010110101011010100010111 /
b1110011111000101110110111110100001000110011101110111101111000010 +
b111111011000010110101010111101 :
b1110001000101011001101010101011100100101010000010000000000 )
b100101100110001110011011011000000000000000000000 0
b11101010001110110010001101000111100011010100110001001100000 ,
14
b11110000100111110101111100000 ;
1!
#3200
0!
#3250
b10111101011100101011110100 3
b11011001010101101011001101101111 .
b101111010111001010111101000000000000000000 2
b1001010000001000000000000000000 *
b11001100100010100000000000000000 1
b1001011001100101101000011010 -
19
b10010000110010100110000000110111 (
b10010000110010100110000000110111 /
b10000001110100110110010101011010110011011011110111010010100010 +
b10000000011000010110101010111101 :
b111011000101010010100000010000000000000000000000000000000000 )
b1111111111111110110011001000101000000000000000000000000000000000 0
b1111000100001001000010010110011001011010000110100000000000000000 ,
04
b11000010100000100000000000000000 ;
1!
#3300
0!
#3350
b11111100000011000011010100001001 3
b10101010000000010001111001000 .
b1111111111111111111111000000110000110101000010010001000111001101 2
b10011101001011001110111011010001 *
b10100000011111011110000100010011 1
b1111100100111010111001100101000 -
09
b10000100011111011111011111110000 (
b10000100011111011111011111110000 /
b100001000100000101010100000000100011110010001111010111011000 +
b1011001101110000001111000101100 :
b1101100011010100111010010110011101110110100010100101111010001 )
b1101000000111110111100001000100110000000000000000 0
b1010001000101011111001001110101110011001010001110000000001011 ,
14
b1010011010011000110000000110111 ;
1!
#3400
0!
#3450
b10111101011100101011110100 3
b10101011111101001001011110101101 .
b101111010111001010111101000000000000000000 2
b1001010000001000000000000000000 *
b11001100100010100000000000000000 1
b1001011001100101101000011010 -
19
b1110110011100111010110011001000 (
b1110110011100111010110011001000 /
b1101000110111101010111111010010010111101011010011100101001100 +
b10011010101110000001111000101100 :
b111011000101010010100000010000000000000000000000000000000000 )
b1111111111111110110011001000101000000000000000000000000000000000 0
b1111000100001001000010010110011001011010000110100000000000000000 ,
04
b11000010100000100000000000000000 ;
1!
#3500
0!
#3550
b100001000100011010110001010 3
b10001111000001011001001001111010 .
b1000010001000110101100010100001101011111001 2
b1100111010110111010101101101101 *
b11100110011000101111111101000 1
b10010110010110010001110111001010 -
09
b11011111011011101111110011001 (
b11011111011011101111110011001 /
b1101011000111011100011110000010110010010011110100111011001101010 +
b1000110101011001011010111011001 :
b110010101100011001110101101110101011011011010101110001000000 )
b1000111001100110001011111111010000000000000000000 0
b110111011100100101100101100100011101110010101011110000101000 ,
14
b111000111101011010110011001000 ;
1!
#3600
0!
#3650
b10111101011100101011110100 3
b10001000101010101100101110010110 .
b101111010111001010111101000000000000000000 2
b1001010000001000000000000000000 *
b11001100100010100000000000000000 1
b1001011001100101101000011010 -
19
b10001001011111110001010100011011 (
b10001001011111110001010100011011 /
b1111010111010100010001010101011001011100101100000000110001010 +
b10000111101011001011010111011001 :
b111011000101010010100000010000000000000000000000000000000000 )
b1111111111111110110011001000101000000000000000000000000000000000 0
b1111000100001001000010010110011001011010000110100000000000000000 ,
04
b11000010100000100000000000000000 ;
1!
#3700
0!
